LICENSE.txt
MANIFEST.in
README.rst
setup.cfg
setup.py
data/data_file
radiis.egg-info/PKG-INFO
radiis.egg-info/SOURCES.txt
radiis.egg-info/dependency_links.txt
radiis.egg-info/entry_points.txt
radiis.egg-info/requires.txt
radiis.egg-info/top_level.txt
sample/__init__.py
sample/package_data.dat